tensormc/__init__.py
tensormc/models.py
tensormc-0.0.1.dist-info/LICENSE
tensormc-0.0.1.dist-info/METADATA
tensormc-0.0.1.dist-info/WHEEL
tensormc-0.0.1.dist-info/top_level.txt
tensormc-0.0.1.dist-info/RECORD
